<annotation>
	<folder>dataset</folder>
	<filename>208.jpg</filename>
	<path>/Users/murray/Desktop/Boring-HTML/dataset/208.jpg</path>
	<source>
		<database>Unknown</database>
	</source>
	<size>
		<width>576</width>
		<height>264</height>
		<depth>3</depth>
	</size>
	<segmented>0</segmented>
	<object>
		<name>img</name>
		<pose>Unspecified</pose>
		<truncated>0</truncated>
		<difficult>0</difficult>
		<bndbox>
			<xmin>84</xmin>
			<ymin>129</ymin>
			<xmax>153</xmax>
			<ymax>260</ymax>
		</bndbox>
	</object>
	<object>
		<name>text</name>
		<pose>Unspecified</pose>
		<truncated>0</truncated>
		<difficult>0</difficult>
		<bndbox>
			<xmin>167</xmin>
			<ymin>147</ymin>
			<xmax>196</xmax>
			<ymax>246</ymax>
		</bndbox>
	</object>
	<object>
		<name>dropdown</name>
		<pose>Unspecified</pose>
		<truncated>0</truncated>
		<difficult>0</difficult>
		<bndbox>
			<xmin>92</xmin>
			<ymin>10</ymin>
			<xmax>121</xmax>
			<ymax>128</ymax>
		</bndbox>
	</object>
	<object>
		<name>radio</name>
		<pose>Unspecified</pose>
		<truncated>0</truncated>
		<difficult>0</difficult>
		<bndbox>
			<xmin>215</xmin>
			<ymin>128</ymin>
			<xmax>235</xmax>
			<ymax>146</ymax>
		</bndbox>
	</object>
	<object>
		<name>checkbox</name>
		<pose>Unspecified</pose>
		<truncated>0</truncated>
		<difficult>0</difficult>
		<bndbox>
			<xmin>213</xmin>
			<ymin>161</ymin>
			<xmax>236</xmax>
			<ymax>181</ymax>
		</bndbox>
	</object>
	<object>
		<name>button</name>
		<pose>Unspecified</pose>
		<truncated>0</truncated>
		<difficult>0</difficult>
		<bndbox>
			<xmin>212</xmin>
			<ymin>196</ymin>
			<xmax>237</xmax>
			<ymax>247</ymax>
		</bndbox>
	</object>
</annotation>
